{
  "versions": [
    {
      "version": "UNRELEASED",
      "date": "",
      "changes": {
        "de": [
          { "type": "feature", "text": "Hersteller-, Filament- und Spulen-Übersicht: Auswahl der Einträge pro Seite (25, 50, 100, 150, 200) mit Speicherung im Browser" },
          { "type": "fix", "text": "Label-Druck: Druckvorschau zeigt jetzt nur noch das Label in korrekter Größe (Chrome, Safari, Firefox)" },
          { "type": "feature", "text": "Label-Druck: Einstellungen (Größe, Schriftgröße, QR-Größe, Anzeige-Optionen) werden im Browser gespeichert" },
          { "type": "fix", "text": "PostgreSQL: Datenbank-Migration schlug bei frischer Installation fehl (Tabelle printer_ams_units wurde vor der Timezone-Migration entfernt)" }
        ],
        "en": [
          { "type": "feature", "text": "Manufacturers, filaments and spools list: Configurable page size (25, 50, 100, 150, 200) with browser persistence" },
          { "type": "fix", "text": "Label printing: Print preview now shows only the label in correct size (Chrome, Safari, Firefox)" },
          { "type": "feature", "text": "Label printing: Settings (size, font size, QR size, display options) are saved in the browser" },
          { "type": "fix", "text": "PostgreSQL: Database migration failed on fresh install (printer_ams_units table was removed before timezone migration)" }
        ]
      }
    },
    {
      "version": "1.0.14",
      "date": "",
      "changes": {
        "de": [
          { "type": "fix", "text": "Filamentübersicht: Sortierung nach Typ funktioniert wieder" },
          { "type": "feature", "text": "Neues SpoolmanAPI-Plugin: FilaMan kann jetzt als Spoolman-Ersatz genutzt werden – externe Tools wie Moonraker oder OctoPrint verbinden sich direkt" },
          { "type": "feature", "text": "SpoolmanAPI-Plugin: IP-basierte Zugriffskontrolle für die Spoolman-Schnittstelle konfigurierbar" }
        ],
        "en": [
          { "type": "fix", "text": "Filament overview: Sorting by type works again" },
          { "type": "feature", "text": "New SpoolmanAPI plugin: FilaMan can now be used as a drop-in Spoolman replacement – external tools like Moonraker or OctoPrint connect directly" },
          { "type": "feature", "text": "SpoolmanAPI plugin: Configurable IP-based access control for the Spoolman interface" }
        ]
      }
    },
    {
      "version": "1.0.12",
      "date": "",
      "changes": {
        "de": [
          { "type": "feature", "text": "Filamente & Spulen: Filter-Auswahl (Dropdowns und Gruppierung) wird im Browser gespeichert und beim nächsten Besuch wiederhergestellt" },
          { "type": "fix", "text": "Filamentübersicht: Sortierung nach Typ funktioniert wieder" }
        ],
        "en": [
          { "type": "feature", "text": "Filaments & Spools: Filter selections (dropdowns and grouping) are saved in the browser and restored on next visit" },
          { "type": "fix", "text": "Filament overview: Sorting by type works again" }
        ]
      }
    },
    {
      "version": "1.0.10",
      "date": "",
      "changes": {
        "de": [
          { "type": "fix", "text": "Spulenübersicht zeigt IDs statt Filamentnamen bei mehr als 200 Filamenten in der Datenbank" },
          { "type": "fix", "text": "Plugin-Updates: Version-Cache wird nach Plugin-Installation/-Deinstallation invalidiert" },
          { "type": "feature", "text": "SpoolmanDB Plugin: Durchsuchbares Filament-Dropdown mit Filter-Suche und Farbpunkten" }
        ],
        "en": [
          { "type": "fix", "text": "Spool overview shows IDs instead of filament names when more than 200 filaments exist in the database" },
          { "type": "fix", "text": "Plugin updates: Version cache is now invalidated after plugin install/uninstall" },
          { "type": "feature", "text": "SpoolmanDB Plugin: Searchable filament dropdown with filter search and color dots" }
        ]
      }
    },
    {
      "version": "1.0.8",
      "date": "",
      "changes": {
        "de": [
          { "type": "change", "text": "Plugin-Suche: Plugins werden jetzt von filaman.app statt GitHub abgerufen" }
        ],
        "en": [
          { "type": "change", "text": "Plugin search: Plugins are now fetched from filaman.app instead of GitHub" }
        ]
      }
    },
    {
      "version": "1.0.7",
      "date": "",
      "changes": {
        "de": [
          { "type": "fix", "text": "PostgreSQL-Kompatibilität: Boolean-Standardwerte und JSON-Abfragen in Migrationen und Spoolman-Import korrigiert" },
          { "type": "feature", "text": "Farbkreise in der Filament-Auswahl beim Anlegen neuer Spulen" },
          { "type": "feature", "text": "Seitennavigation mit Seitenzahlen über und unter der Tabelle (Filamente, Spulen, Hersteller)" },
          { "type": "feature", "text": "Aktuelle Seite wird gespeichert und beim Zurückkehren wiederhergestellt" },
          { "type": "change", "text": "Bambu Material Index: Dropdown zeigt nur noch Materialnamen (alphabetisch sortiert) statt technischer Schlüssel" },
          { "type": "feature", "text": "Zeitstempel werden jetzt automatisch in der Zeitzone des Browsers angezeigt" }
        ],
        "en": [
          { "type": "fix", "text": "PostgreSQL compatibility: Fixed boolean default values and JSON queries in migrations and Spoolman import" },
          { "type": "feature", "text": "Color circles in the filament dropdown when creating new spools" },
          { "type": "feature", "text": "Page navigation with page numbers above and below the table (Filaments, Spools, Manufacturers)" },
          { "type": "feature", "text": "Current page is saved and restored when navigating back" },
          { "type": "change", "text": "Bambu Material Index: Dropdown shows only material names (alphabetically sorted) instead of technical keys" },
          { "type": "feature", "text": "Timestamps are now automatically displayed in the browser's timezone" }
        ]
      }
    },
    {
      "version": "1.0.6",
      "date": "",
      "changes": {
        "de": [
          { "type": "fix", "text": "Killswitch (Alle Daten löschen) funktioniert jetzt korrekt" },
          { "type": "feature", "text": "Sortiereinstellungen bleiben jetzt erhalten" },
          { "type": "feature", "text": "Massenbearbeitung in der Spulenübersicht: Löschen, Standort, Status, Schwellenwert, Leergewicht und Preis für mehrere Spulen gleichzeitig setzen" },
          { "type": "feature", "text": "Filamente können jetzt nach Hersteller gruppiert werden" },
          { "type": "change", "text": "Spaltenreihenfolge in der Filamentübersicht: Hersteller und Typ stehen jetzt vorn" },
          { "type": "feature", "text": "Massenbearbeitung in der Filamentübersicht: Löschen, Preis, Durchmesser, Spulengewicht und Dichte für mehrere Filamente gleichzeitig setzen" }
        ],
        "en": [
          { "type": "fix", "text": "Killswitch (Delete all data) now works correctly" },
          { "type": "feature", "text": "Sort settings are now preserved" },
          { "type": "feature", "text": "Bulk editing in spool overview: Delete, set location, status, threshold, empty weight and price for multiple spools at once" },
          { "type": "feature", "text": "Filaments can now be grouped by manufacturer" },
          { "type": "change", "text": "Column order in filament overview: Manufacturer and type are now shown first" },
          { "type": "feature", "text": "Bulk editing in filament overview: Delete, set price, diameter, spool weight and density for multiple filaments at once" }
        ]
      }
    },
    {
      "version": "1.0.2",
      "date": "",
      "changes": {
        "de": [
          { "type": "feature", "text": "OIDC (OAuth2) Login: Single Sign-On über OpenID Connect für bestehende Benutzer" },
          { "type": "feature", "text": "OIDC-Konfigurationsseite im Admin-Bereich mit Aktivierung, Provider-Einstellungen und Callback-URL" },
          { "type": "feature", "text": "Konfigurierbarer SSO-Button auf der Login-Seite" }
        ],
        "en": [
          { "type": "feature", "text": "OIDC (OAuth2) Login: Single Sign-On via OpenID Connect for existing users" },
          { "type": "feature", "text": "OIDC configuration page in admin area with activation, provider settings and callback URL" },
          { "type": "feature", "text": "Configurable SSO button on the login page" }
        ]
      }
    },
    {
      "version": "0.3.11",
      "date": "2026-02-27",
      "changes": {
        "de": [
          { "type": "feature", "text": "Neues Changelog-Popup zeigt Neuigkeiten nach jedem Update" },
          { "type": "feature", "text": "Changelog-Seite mit vollständiger Versionshistorie" },
          { "type": "feature", "text": "Versionsinformationen auf der Admin-Seite: Installierte und neueste Version auf einen Blick" },
          { "type": "feature", "text": "Automatische Prüfung auf System- und Plugin-Updates (alle 24h)" }
        ],
        "en": [
          { "type": "feature", "text": "New changelog popup shows what's new after each update" },
          { "type": "feature", "text": "Changelog page with full version history" },
          { "type": "feature", "text": "Version info on admin page: Installed and latest version at a glance" },
          { "type": "feature", "text": "Automatic check for system and plugin updates (every 24h)" }
        ]
      }
    },
    {
      "version": "0.3.9",
      "date": "2026-02-27",
      "changes": {
        "de": [
          { "type": "feature", "text": "Spulen und Filamente können jetzt dupliziert werden" },
          { "type": "feature", "text": "Mehrere Spulen auf einmal anlegen" },
          { "type": "feature", "text": "Alle leeren Spulen vom Dashboard aus auf einmal archivieren" },
          { "type": "feature", "text": "Spoolman-Import: Bestehende Daten aus Spoolman übernehmen" },
          { "type": "feature", "text": "Eigene Zusatzfelder für Spulen und Filamente definieren" },
          { "type": "feature", "text": "Neues Plugin-System für einfache Erweiterungen" },
          { "type": "feature", "text": "Mehrfarbige Filamente unterstützt" },
          { "type": "feature", "text": "Spulen können archiviert statt gelöscht werden" },
          { "type": "change", "text": "BambuLab-Anbindung ist jetzt ein separates Plugin" },
          { "type": "change", "text": "Plugins können einzeln aktiviert und deaktiviert werden" },
          { "type": "change", "text": "Verbesserte Plugin-Verwaltung im Admin-Bereich" },
          { "type": "fix", "text": "Driver Shutdown Blockade behoben" }
        ],
        "en": [
          { "type": "feature", "text": "Spools and filaments can now be duplicated" },
          { "type": "feature", "text": "Create multiple spools at once" },
          { "type": "feature", "text": "Archive all empty spools from the dashboard at once" },
          { "type": "feature", "text": "Spoolman Import: Migrate existing data from Spoolman" },
          { "type": "feature", "text": "Define custom extra fields for spools and filaments" },
          { "type": "feature", "text": "New plugin system for easy extensions" },
          { "type": "feature", "text": "Multi-color filaments supported" },
          { "type": "feature", "text": "Spools can be archived instead of deleted" },
          { "type": "change", "text": "BambuLab integration is now a separate plugin" },
          { "type": "change", "text": "Plugins can be individually activated and deactivated" },
          { "type": "change", "text": "Improved plugin management in admin area" },
          { "type": "fix", "text": "Fixed driver shutdown hang" }
        ]
      }
    }
  ]
}
